yi_package.py
yi_package-0.1.0.dist-info/LICENSE
yi_package-0.1.0.dist-info/WHEEL
yi_package-0.1.0.dist-info/METADATA
yi_package-0.1.0.dist-info/RECORD
